faker_music/__init__.py
faker_music/genres.py
faker_music/instruments.py
faker_music/music.py
faker_music/tests/__init__.py
faker_music/tests/conftest.py
faker_music/tests/test_music.py
faker_music-0.4.dist-info/LICENSE
faker_music-0.4.dist-info/WHEEL
faker_music-0.4.dist-info/METADATA
faker_music-0.4.dist-info/RECORD
