Metadata-Version: 1.1
Name: faker_music
Version: 0.4
Summary: Music Faker Community Provider
Home-page: https://github.com/jeffwright13/faker_music/
Author: Jeff Wright
Author-email: jeff.washcloth@gmail.com
